DIYables_Pico_Button/DIYables_Pico_Button.py
DIYables_Pico_Button/__init__.py
DIYables_Pico_Button-0.1.1.dist-info/LICENSE
DIYables_Pico_Button-0.1.1.dist-info/METADATA
DIYables_Pico_Button-0.1.1.dist-info/WHEEL
DIYables_Pico_Button-0.1.1.dist-info/top_level.txt
DIYables_Pico_Button-0.1.1.dist-info/RECORD
